{
  "tone_id": "winter_cool_light",
  "query": "아이스 핑크 니트 겨울",
  "collected_at": "2026-03-28T23:10:11.825550",
  "count": 100,
  "items": [
    {
      "title": "여성 <b>니트</b> 박시 상의 얇은 <b>핑크</b> <b>아이스</b> 여 반팔 여름 루즈핏 날씬 식",
      "link": "https://smartstore.naver.com/main/products/8939631532",
      "image": "https://shopping-phinf.pstatic.net/main_8648413/86484131851.jpg",
      "lprice": "27450",
      "hprice": "",
      "mall_name": "직구항공",
      "product_id": "86484131851",
      "category1": "패션의류",
      "category2": "여성의류",
      "category3": "니트",
      "category4": "풀오버"
    },
    {
      "title": "화이트 그린 블루 퍼플 <b>핑크</b> V넥 <b>아이스</b> 실크 플리츠 <b>니트</b> 스웨터 시스루 탑 슬림 셔츠",
      "link": "https://smartstore.naver.com/main/products/6834618695",
      "image": "https://shopping-phinf.pstatic.net/main_8437911/84379119015.jpg",
      "lprice": "48960",
      "hprice": "",
      "mall_name": "로이옙",
      "product_id": "84379119015",
      "category1": "패션의류",
      "category2": "여성의류",
      "category3": "니트",
      "category4": "풀오버"
    },
    {
      "title": "여성 <b>니트</b> 반팔티 라운드 <b>핑크</b> <b>아이스</b> 반팔 티셔츠 여 여름 프렌치 시크 유니크 디자인 시",
      "link": "https://smartstore.naver.com/main/products/8788082357",
      "image": "https://shopping-phinf.pstatic.net/main_8633258/86332582680.jpg",
      "lprice": "29500",
      "hprice": "",
      "mall_name": "직구항공",
      "product_id": "86332582680",
      "category1": "패션의류",
      "category2": "여성의류",
      "category3": "니트",
      "category4": "풀오버"
    },
    {
      "title": "여성 카라 <b>니트</b> 반팔티 <b>핑크</b> 넥 <b>아이스</b> 반팔티 여 여름 디자인 감각 소박한 슬림 브이넥",
      "link": "https://smartstore.naver.com/main/products/8811513108",
      "image": "https://shopping-phinf.pstatic.net/main_8635601/86356013430.jpg",
      "lprice": "29750",
      "hprice": "",
      "mall_name": "키즈캐슬1",
      "product_id": "86356013430",
      "category1": "패션의류",
      "category2": "여성의류",
      "category3": "니트",
      "category4": "풀오버"
    },
    {
      "title": "여성 크롭 <b>니트</b> 티셔츠 브이넥 <b>핑크</b> <b>아이스</b> 반팔 여 여름 얇은 하이웨스트 카디건 쇼트 상",
      "link": "https://smartstore.naver.com/main/products/8772304233",
      "image": "https://shopping-phinf.pstatic.net/main_8631680/86316804552.jpg",
      "lprice": "27450",
      "hprice": "",
      "mall_name": "키즈캐슬1",
      "product_id": "86316804552",
      "category1": "패션의류",
      "category2": "여성의류",
      "category3": "니트",
      "category4": "풀오버"
    },
    {
      "title": "여성 <b>니트</b> 박시 상의 순욱 <b>핑크</b> <b>아이스</b> 여 여름 얇은 루즈핏 반팔 티셔츠 작은 키",
      "link": "https://smartstore.naver.com/main/products/8939631702",
      "image": "https://shopping-phinf.pstatic.net/main_8648413/86484132024.jpg",
      "lprice": "34750",
      "hprice": "",
      "mall_name": "직구항공",
      "product_id": "86484132024",
      "category1": "패션의류",
      "category2": "여성의류",
      "category3": "니트",
      "category4": "풀오버"
    },
    {
      "title": "여성 <b>니트</b> 반팔티 라운드 <b>아이스 핑크</b> 여 여름 핫걸 슬림핏 티셔츠 얇은 쇼트 상의",
      "link": "https://smartstore.naver.com/main/products/8787997601",
      "image": "https://shopping-phinf.pstatic.net/main_8633249/86332497924.jpg",
      "lprice": "24750",
      "hprice": "",
      "mall_name": "제이원88",
      "product_id": "86332497924",
      "category1": "패션의류",
      "category2": "여성의류",
      "category3": "니트",
      "category4": "풀오버"
    },
    {
      "title": "2025년 여름 V넥 <b>아이스</b> 실크 스웨터 반팔 여성용 나비 디테일 다림질 다이아몬드 탑 데일리 <b>니트</b> pink",
      "link": "https://smartstore.naver.com/main/products/12025029322",
      "image": "https://shopping-phinf.pstatic.net/main_8956954/89569540014.jpg",
      "lprice": "48500",
      "hprice": "",
      "mall_name": "페라라패션",
      "product_id": "89569540014",
      "category1": "패션의류",
      "category2": "여성의류",
      "category3": "니트",
      "category4": "풀오버"
    },
    {
      "title": "막스마라 아울렛 인트렌드 타이트 리브 <b>니트</b> <b>아이스</b> 3361064102001 GARAGE [관부가세포함가]",
      "link": "https://firstboutique.kr/product/detail.html?product_no=704759&cate_no=19675&display_group=1&cafe_mkt=naver_ks&mkt_in=Y&ghost_mall_id=naver&ref=naver_open",
      "image": "https://shopping-phinf.pstatic.net/main_5907977/59079777763.jpg",
      "lprice": "193800",
      "hprice": "",
      "mall_name": "퍼스트부티크",
      "product_id": "59079777763",
      "category1": "패션의류",
      "category2": "여성의류",
      "category3": "니트",
      "category4": "풀오버"
    },
    {
      "title": "<b>니트</b> 여성<b>니트</b> 실크 브이넥 <b>핑크니트</b> 여름 여자<b>니트</b> 뜨개질 얇은 <b>아이스</b> 루즈핏 가디건",
      "link": "https://search.shopping.naver.com/catalog/41903464222",
      "image": "https://shopping-phinf.pstatic.net/main_4190346/41903464222.20230817010346.jpg",
      "lprice": "21170",
      "hprice": "",
      "mall_name": "네이버",
      "product_id": "41903464222",
      "category1": "패션의류",
      "category2": "여성의류",
      "category3": "니트",
      "category4": "풀오버"
    },
    {
      "title": "브이넥 홀로우 <b>아이스</b>실크 브이넥<b>니트</b> 여성<b>니트</b> 홀로우<b>니트 겨울</b><b>니트</b> 얇은<b>니트</b> <b>니트</b>탑 흰색",
      "link": "https://smartstore.naver.com/main/products/11917406882",
      "image": "https://shopping-phinf.pstatic.net/main_8946191/89461917491.jpg",
      "lprice": "29000",
      "hprice": "",
      "mall_name": "소연maket",
      "product_id": "89461917491",
      "category1": "패션의류",
      "category2": "여성의류",
      "category3": "니트",
      "category4": "풀오버"
    },
    {
      "title": "여성 <b>핑크</b> <b>아이스</b> 실크 스웨터 티셔츠 인기 여름 경량 통기성 긴팔티",
      "link": "https://smartstore.naver.com/main/products/11722210444",
      "image": "https://shopping-phinf.pstatic.net/main_8926672/89266720943.jpg",
      "lprice": "27200",
      "hprice": "",
      "mall_name": "바잉어스스토어",
      "product_id": "89266720943",
      "category1": "패션의류",
      "category2": "여성의류",
      "category3": "니트",
      "category4": "풀오버"
    },
    {
      "title": "폴로<b>니트</b> 여자반팔 기능성카라티 <b>아이스</b> 반팔티 <b>핑크</b> 여름 중년",
      "link": "https://smartstore.naver.com/main/products/8553516142",
      "image": "https://shopping-phinf.pstatic.net/main_8609801/86098016464.jpg",
      "lprice": "42860",
      "hprice": "",
      "mall_name": "쾌속직구",
      "product_id": "86098016464",
      "category1": "패션의류",
      "category2": "여성의류",
      "category3": "니트",
      "category4": "풀오버"
    },
    {
      "title": "중공 v 넥 <b>아이스</b> 실크 스웨터 반팔 <b>니트</b> 얇은 쇄골 탑 <b>겨울</b> 블라우스",
      "link": "https://smartstore.naver.com/main/products/10679958830",
      "image": "https://shopping-phinf.pstatic.net/main_8822446/88224464752.jpg",
      "lprice": "18330",
      "hprice": "",
      "mall_name": "굴러온부업",
      "product_id": "88224464752",
      "category1": "패션의류",
      "category2": "여성의류",
      "category3": "니트",
      "category4": "풀오버"
    },
    {
      "title": "MEFUN 반팔 <b>니트</b>티 여성 라운드 여름 <b>아이스</b> 반팔티 쿨<b>니트</b>  <b>핑크</b>  L-66/95",
      "link": "https://link.coupang.com/re/PCSNAVERPCSDP?pageKey=8801499410&ctag=8801499410&lptag=V92653157277&itemId=25629062106&vendorItemId=92653157277&spec=10305198",
      "image": "https://shopping-phinf.pstatic.net/main_5533369/55333696177.jpg",
      "lprice": "9990",
      "hprice": "",
      "mall_name": "쿠팡",
      "product_id": "55333696177",
      "category1": "패션의류",
      "category2": "여성의류",
      "category3": "니트",
      "category4": "풀오버"
    },
    {
      "title": "여성 리본 장식 라운드 <b>니트</b> 스웨터 과 <b>겨울</b> 랜턴 소매 셔츠 스티칭 보우 <b>아이스</b> 실크",
      "link": "https://smartstore.naver.com/main/products/6338955501",
      "image": "https://shopping-phinf.pstatic.net/main_8388345/83883457989.jpg",
      "lprice": "32000",
      "hprice": "",
      "mall_name": "미리별쇼핑",
      "product_id": "83883457989",
      "category1": "패션의류",
      "category2": "여성의류",
      "category3": "니트",
      "category4": "풀오버"
    },
    {
      "title": "<b>핑크</b>색 <b>니트</b> 상의 여 여름 <b>아이스</b> 선염 숏 언발 슬림 긴팔감 <b>핑크</b> 가디건 얇은 <b>니트</b>",
      "link": "https://smartstore.naver.com/main/products/6161064640",
      "image": "https://shopping-phinf.pstatic.net/main_8370556/83705564217.jpg",
      "lprice": "27400",
      "hprice": "",
      "mall_name": "아이템49",
      "product_id": "83705564217",
      "category1": "패션의류",
      "category2": "여성의류",
      "category3": "니트",
      "category4": "풀오버"
    },
    {
      "title": "슬림한 블루 폴로넥 <b>아이스</b> 실크 반팔 <b>니트</b> 고급스러운 여름 숏 스타일 2025 탑 <b>핑크</b>",
      "link": "https://smartstore.naver.com/main/products/11969527303",
      "image": "https://shopping-phinf.pstatic.net/main_8951403/89514037991.jpg",
      "lprice": "21800",
      "hprice": "",
      "mall_name": "리스본제이",
      "product_id": "89514037991",
      "category1": "패션의류",
      "category2": "여성의류",
      "category3": "니트",
      "category4": "풀오버"
    },
    {
      "title": "<b>핑크</b> 여름 폴카 <b>니트</b> 탑 여성 카디건 도트 숏 실크 긴 썸 얇은 <b>아이스</b> 프로텍션 소매 XL",
      "link": "https://smartstore.naver.com/main/products/12379534909",
      "image": "https://shopping-phinf.pstatic.net/main_8992404/89924045626.jpg",
      "lprice": "41100",
      "hprice": "",
      "mall_name": "IN THE OUTLET",
      "product_id": "89924045626",
      "category1": "패션의류",
      "category2": "여성의류",
      "category3": "니트",
      "category4": "풀오버"
    },
    {
      "title": "<b>아이스</b> <b>니트</b> 크롭 볼레로 얇은 긴소매 가디건 숄 래시가드 아우터 봄 원피스 코디",
      "link": "https://smartstore.naver.com/main/products/8856666538",
      "image": "https://shopping-phinf.pstatic.net/main_8640116/86401166861.jpg",
      "lprice": "11200",
      "hprice": "",
      "mall_name": "핑크파트라",
      "product_id": "86401166861",
      "category1": "패션의류",
      "category2": "여성의류",
      "category3": "니트",
      "category4": "카디건"
    },
    {
      "title": "<b>아이스</b> <b>니트</b> 크롭 볼레로 얇은 긴소매 가디건 숄 래시가드 아우터 봄 원피스 코디",
      "link": "https://smartstore.naver.com/main/products/8856676989",
      "image": "https://shopping-phinf.pstatic.net/main_8640117/86401177312.jpg",
      "lprice": "12500",
      "hprice": "",
      "mall_name": "핑크파트라",
      "product_id": "86401177312",
      "category1": "패션의류",
      "category2": "여성의류",
      "category3": "니트",
      "category4": "카디건"
    },
    {
      "title": "하늘색<b>니트</b> 노르딕패턴 어글리스웨터 <b>아이스</b>블루 눈꽃<b>니트</b> 캔디블루 빈티지 풀오버",
      "link": "https://smartstore.naver.com/main/products/9745771416",
      "image": "https://shopping-phinf.pstatic.net/main_8729027/87290273689.jpg",
      "lprice": "37900",
      "hprice": "",
      "mall_name": "Shop LICORICE",
      "product_id": "87290273689",
      "category1": "패션의류",
      "category2": "여성의류",
      "category3": "니트",
      "category4": "풀오버"
    },
    {
      "title": "탑트레일 여름 <b>아이스</b> 하트 포인트 <b>니트</b>반팔티 여름<b>니트</b> 여름반팔 시원한티 통기성좋은티  <b>핑크</b>",
      "link": "https://link.coupang.com/re/PCSNAVERPCSDP?pageKey=8778494362&ctag=8778494362&lptag=P8778494362&itemId=25540556331&vendorItemId=92532116423&spec=10305198",
      "image": "https://shopping-phinf.pstatic.net/main_5481579/54815797049.103.jpg",
      "lprice": "19900",
      "hprice": "",
      "mall_name": "쿠팡",
      "product_id": "54815797049",
      "category1": "패션의류",
      "category2": "여성의류",
      "category3": "니트",
      "category4": "풀오버"
    },
    {
      "title": "[롯데백화점](롯데백화점)<b>아이스</b>터치 반팔 카라 <b>핑크 니트</b>(클래식핏)DKTXB02",
      "link": "https://link.gmarket.co.kr/gate/pcs?item-no=4706953454&sub-id=1003&service-code=10000003&lcd=100000104",
      "image": "https://shopping-phinf.pstatic.net/main_5936221/59362216034.jpg",
      "lprice": "54630",
      "hprice": "",
      "mall_name": "G마켓",
      "product_id": "59362216034",
      "category1": "패션의류",
      "category2": "여성의류",
      "category3": "니트",
      "category4": "풀오버"
    },
    {
      "title": "[롯데백화점](롯데백화점)<b>아이스</b>터치 반팔 카라 <b>핑크 니트</b>(클래식핏)DKTXB02",
      "link": "https://link.auction.co.kr/gate/pcs?item-no=F513188518&sub-id=1&service-code=10000003",
      "image": "https://shopping-phinf.pstatic.net/main_5936194/59361947256.jpg",
      "lprice": "54630",
      "hprice": "",
      "mall_name": "옥션",
      "product_id": "59361947256",
      "category1": "패션의류",
      "category2": "여성의류",
      "category3": "니트",
      "category4": "풀오버"
    },
    {
      "title": "<b>니트</b> 반팔티 티셔츠 V라인 <b>핑크</b> 반팔 <b>아이스</b> 티셔츠 주름 여여름 얇고 부드러운 시크 상의",
      "link": "https://smartstore.naver.com/main/products/8776072402",
      "image": "https://shopping-phinf.pstatic.net/main_8632057/86320572725.jpg",
      "lprice": "29980",
      "hprice": "",
      "mall_name": "직구항공",
      "product_id": "86320572725",
      "category1": "패션의류",
      "category2": "여성의류",
      "category3": "니트",
      "category4": "풀오버"
    },
    {
      "title": "여성 <b>니트</b> 반팔티 라운드 요정의 <b>핑크</b> 반팔 <b>아이스</b> 가디건 여 여름 디자인 감각 하트 장식",
      "link": "https://smartstore.naver.com/main/products/8788047519",
      "image": "https://shopping-phinf.pstatic.net/main_8633254/86332547842.jpg",
      "lprice": "29980",
      "hprice": "",
      "mall_name": "최강직구",
      "product_id": "86332547842",
      "category1": "패션의류",
      "category2": "여성의류",
      "category3": "니트",
      "category4": "풀오버"
    },
    {
      "title": "여성 <b>니트</b> 박시 상의 퍼플 여름 여성 래쉬가드 루즈핏 오프숄더 <b>핑크</b> 얇은 <b>아이스</b> 여",
      "link": "https://smartstore.naver.com/main/products/8939631716",
      "image": "https://shopping-phinf.pstatic.net/main_8648413/86484132037.jpg",
      "lprice": "27250",
      "hprice": "",
      "mall_name": "직구항공",
      "product_id": "86484132037",
      "category1": "패션의류",
      "category2": "여성의류",
      "category3": "니트",
      "category4": "풀오버"
    },
    {
      "title": "<b>아이스</b><b>니트</b> 리본꼬임 여름 골지<b>니트</b> 아이 <b>핑크</b> 블랙(3color)",
      "link": "https://smartstore.naver.com/main/products/12062011989",
      "image": "https://shopping-phinf.pstatic.net/main_8960652/89606522688.jpg",
      "lprice": "41600",
      "hprice": "",
      "mall_name": "버터베이지",
      "product_id": "89606522688",
      "category1": "패션의류",
      "category2": "여성의류",
      "category3": "니트",
      "category4": "풀오버"
    },
    {
      "title": "여성<b>니트</b>티 반팔 긴팔 베이직 봄 여름 패션 <b>아이스</b> 실크 <b>니트</b> 스웨터 넥 솔리드 심플 캐주얼 탑",
      "link": "https://smartstore.naver.com/main/products/7334061306",
      "image": "https://shopping-phinf.pstatic.net/main_8487856/84878561628.jpg",
      "lprice": "95000",
      "hprice": "",
      "mall_name": "무심스토어 둘",
      "product_id": "84878561628",
      "category1": "패션의류",
      "category2": "여성의류",
      "category3": "니트",
      "category4": "풀오버"
    },
    {
      "title": "제이베니 오버사이즈 통통녀 패치 케이프 루즈핏 얇은 <b>아이스</b> 실크 <b>니트</b> 반팔 상의 검정 M(60kg 이하)",
      "link": "https://smartstore.naver.com/main/products/11793721587",
      "image": "https://shopping-phinf.pstatic.net/main_8933823/89338232174.jpg",
      "lprice": "39000",
      "hprice": "",
      "mall_name": "디노베니",
      "product_id": "89338232174",
      "category1": "패션의류",
      "category2": "여성의류",
      "category3": "니트",
      "category4": "풀오버"
    },
    {
      "title": "<b>아이스</b><b>니트</b> 어깨패드 반팔 얇은 <b>핑크</b> 찡 메탈 라운드넥 <b>니트</b>",
      "link": "https://smartstore.naver.com/main/products/10693800619",
      "image": "https://shopping-phinf.pstatic.net/main_8823830/88238306541.jpg",
      "lprice": "49000",
      "hprice": "",
      "mall_name": "프리티레이디스",
      "product_id": "88238306541",
      "category1": "패션의류",
      "category2": "여성의류",
      "category3": "니트",
      "category4": "풀오버"
    },
    {
      "title": "레이어드 골지나 시 블랙 나시티 이 너나시 플리츠 <b>핑크</b> 여성 <b>아이스</b> 나시",
      "link": "https://smartstore.naver.com/main/products/12502163236",
      "image": "https://shopping-phinf.pstatic.net/main_9004667/90046674089.jpg",
      "lprice": "13080",
      "hprice": "",
      "mall_name": "트리피샵",
      "product_id": "90046674089",
      "category1": "패션의류",
      "category2": "여성의류",
      "category3": "니트",
      "category4": "풀오버"
    },
    {
      "title": "여성 크롭 <b>니트</b> 티셔츠 스위트 <b>핑크</b> 숏 <b>아이스</b> 가디건 하이웨스트 얇은 코트 반팔 상의 복",
      "link": "https://smartstore.naver.com/main/products/8772304243",
      "image": "https://shopping-phinf.pstatic.net/main_8631680/86316804560.jpg",
      "lprice": "37250",
      "hprice": "",
      "mall_name": "키즈캐슬1",
      "product_id": "86316804560",
      "category1": "패션의류",
      "category2": "여성의류",
      "category3": "니트",
      "category4": "풀오버"
    },
    {
      "title": "여성 <b>니트</b> 반팔티 <b>아이스</b> 얇은 티셔츠 배색 반팔 <b>핑크</b> S",
      "link": "https://smartstore.naver.com/main/products/12754047881",
      "image": "https://shopping-phinf.pstatic.net/main_9029855/90298558830.1.jpg",
      "lprice": "27400",
      "hprice": "",
      "mall_name": "자연소울",
      "product_id": "90298558830",
      "category1": "패션의류",
      "category2": "여성의류",
      "category3": "니트",
      "category4": "풀오버"
    },
    {
      "title": "기능성카라티 폴로<b>니트</b> 여자반팔 유니크 <b>핑크</b> 향기로운 <b>아이스</b> 여름",
      "link": "https://smartstore.naver.com/main/products/8553507426",
      "image": "https://shopping-phinf.pstatic.net/main_8609800/86098007749.jpg",
      "lprice": "48670",
      "hprice": "",
      "mall_name": "쾌속직구",
      "product_id": "86098007749",
      "category1": "패션의류",
      "category2": "여성의류",
      "category3": "니트",
      "category4": "풀오버"
    },
    {
      "title": "여자폴로카라티 여름<b>니트</b> 캐주얼 <b>핑크</b> 스트라이프 펀칭 반팔 <b>아이스</b> 여름",
      "link": "https://smartstore.naver.com/main/products/8553532281",
      "image": "https://shopping-phinf.pstatic.net/main_8609803/86098032600.jpg",
      "lprice": "24230",
      "hprice": "",
      "mall_name": "쾌속직구",
      "product_id": "86098032600",
      "category1": "패션의류",
      "category2": "여성의류",
      "category3": "니트",
      "category4": "풀오버"
    },
    {
      "title": "여성 여름에 입기 옐로우 <b>핑크</b> 반팔 <b>아이스</b>블루 여성반팔<b>니트</b> 반팔<b>니트</b>티셔츠",
      "link": "https://smartstore.naver.com/main/products/11968348744",
      "image": "https://shopping-phinf.pstatic.net/main_8951285/89512859432.jpg",
      "lprice": "40890",
      "hprice": "",
      "mall_name": "오또또몰",
      "product_id": "89512859432",
      "category1": "패션의류",
      "category2": "여성의류",
      "category3": "니트",
      "category4": "풀오버"
    },
    {
      "title": "<b>겨울</b> 탑 <b>니트</b> 끈나시 스레드 <b>아이스</b> 캐미솔 소형 티셔츠 슬림 싱글투피스",
      "link": "https://smartstore.naver.com/main/products/11002925519",
      "image": "https://shopping-phinf.pstatic.net/main_8854743/88547431609.jpg",
      "lprice": "22200",
      "hprice": "",
      "mall_name": "MK-찍꾸찌꾸",
      "product_id": "88547431609",
      "category1": "패션의류",
      "category2": "여성의류",
      "category3": "니트",
      "category4": "풀오버"
    },
    {
      "title": "스퀘어넥 <b>니트</b> 반팔<b>니트</b> 여성 얇은 봄 여름 가을 레이어드 프론트 숄더 <b>핑크</b> <b>아이스</b> 실크 반팔 티셔츠 디자인 감각 틈새 슬림 짧은 스웨터 탑",
      "link": "https://smartstore.naver.com/main/products/10010855778",
      "image": "https://shopping-phinf.pstatic.net/main_8755535/87555358139.jpg",
      "lprice": "38100",
      "hprice": "",
      "mall_name": "Prosperar",
      "product_id": "87555358139",
      "category1": "패션의류",
      "category2": "여성의류",
      "category3": "니트",
      "category4": "풀오버"
    },
    {
      "title": "옷사이트 기본템 V넥<b>니트</b> 꾸안꾸 <b>아이스</b> 이너 패션 봄 <b>겨울</b> 빅사이즈 상의",
      "link": "https://smartstore.naver.com/main/products/9184517449",
      "image": "https://shopping-phinf.pstatic.net/main_8672901/86729017769.jpg",
      "lprice": "33360",
      "hprice": "",
      "mall_name": "직구척척",
      "product_id": "86729017769",
      "category1": "패션의류",
      "category2": "여성의류",
      "category3": "니트",
      "category4": "풀오버"
    },
    {
      "title": "망사 반팔 <b>니트</b> 펀칭 요정의 포켓 <b>핑크</b> <b>아이스</b> 여 여름 아우터 블라우스 자외선 차단 디자",
      "link": "https://smartstore.naver.com/main/products/8834573825",
      "image": "https://shopping-phinf.pstatic.net/main_8637907/86379074147.jpg",
      "lprice": "78750",
      "hprice": "",
      "mall_name": "최강직구",
      "product_id": "86379074147",
      "category1": "패션의류",
      "category2": "여성의류",
      "category3": "니트",
      "category4": "풀오버"
    },
    {
      "title": "[아마존 공식]Greg Norman 여성용 모나키 <b>니트</b> 플릿 스코트 <b>핑크</b> <b>아이스</b> L",
      "link": "https://www.11st.co.kr/connect/Gateway.tmall?method=Xsite&prdNo=3530371181&tid=1000000061",
      "image": "https://shopping-phinf.pstatic.net/main_4412167/44121679533.7.jpg",
      "lprice": "102480",
      "hprice": "",
      "mall_name": "11번가",
      "product_id": "44121679533",
      "category1": "패션의류",
      "category2": "여성의류",
      "category3": "니트",
      "category4": "풀오버"
    },
    {
      "title": "시스루 <b>니트</b> <b>아이스</b> 실크 여성 봄 가을 <b>겨울</b> 얇은 긴팔 자외선 차단 셔츠 흰색 중공 탑",
      "link": "https://smartstore.naver.com/main/products/10490007848",
      "image": "https://shopping-phinf.pstatic.net/main_8803451/88034513149.jpg",
      "lprice": "27340",
      "hprice": "",
      "mall_name": "굴러온부업",
      "product_id": "88034513149",
      "category1": "패션의류",
      "category2": "여성의류",
      "category3": "니트",
      "category4": "풀오버"
    },
    {
      "title": "망사 반팔 <b>니트</b> 펀칭 <b>핑크</b> 스트라이프 넥 반팔 <b>아이스</b> 여 여름 루즈핏 캐주얼 티셔츠 패션",
      "link": "https://smartstore.naver.com/main/products/8834581832",
      "image": "https://shopping-phinf.pstatic.net/main_8637908/86379082150.jpg",
      "lprice": "27250",
      "hprice": "",
      "mall_name": "직구항공",
      "product_id": "86379082150",
      "category1": "패션의류",
      "category2": "여성의류",
      "category3": "니트",
      "category4": "풀오버"
    },
    {
      "title": "JIEVE 여자 여름 <b>아이스</b> 얇은 날개 소매 <b>핑크 니트</b> 디자인 펀칭 타이트 숏 상의 SZ051718  S",
      "link": "https://link.coupang.com/re/PCSNAVERPCSDP?pageKey=8779975164&ctag=8779975164&lptag=P8779975164&itemId=25545616852&vendorItemId=92537129558&spec=10305199",
      "image": "https://shopping-phinf.pstatic.net/main_5482982/54829828958.jpg",
      "lprice": "19040",
      "hprice": "",
      "mall_name": "쿠팡",
      "product_id": "54829828958",
      "category1": "패션의류",
      "category2": "여성의류",
      "category3": "니트",
      "category4": "풀오버"
    },
    {
      "title": "엄마 중년여성 스웨터 <b>니트</b> 간절기 품 가을 <b>겨울</b> 옷 <b>아이스</b>실크 긴팔 티셔츠 노년 할머니 얇",
      "link": "https://smartstore.naver.com/main/products/11825433723",
      "image": "https://shopping-phinf.pstatic.net/main_8936994/89369944310.jpg",
      "lprice": "60400",
      "hprice": "",
      "mall_name": "프리브몰",
      "product_id": "89369944310",
      "category1": "패션의류",
      "category2": "여성의류",
      "category3": "니트",
      "category4": "풀오버"
    },
    {
      "title": "<b>니트</b> 반팔티 프렌치 브이넥 여름 <b>아이스</b> 티셔츠 반팔티 <b>핑크</b>",
      "link": "https://smartstore.naver.com/main/products/10418519110",
      "image": "https://shopping-phinf.pstatic.net/main_8796302/87963024095.jpg",
      "lprice": "31290",
      "hprice": "",
      "mall_name": "함께하는 일상",
      "product_id": "87963024095",
      "category1": "패션의류",
      "category2": "여성의류",
      "category3": "니트",
      "category4": "풀오버"
    },
    {
      "title": "해피유통 여성 브이넥 슬림 얇은 <b>아이스</b> <b>니트</b> 탑 jhlyt  무료  <b>핑크</b>",
      "link": "https://link.coupang.com/re/PCSNAVERPCSDP?pageKey=8984631384&ctag=8984631384&lptag=V93287683628&itemId=26310102093&vendorItemId=93287683628&spec=10305199",
      "image": "https://shopping-phinf.pstatic.net/main_5942652/59426523804.jpg",
      "lprice": "15470",
      "hprice": "",
      "mall_name": "쿠팡",
      "product_id": "59426523804",
      "category1": "패션의류",
      "category2": "여성의류",
      "category3": "니트",
      "category4": "풀오버"
    },
    {
      "title": "가디건 브레스트 루즈핏 실크 <b>핑크니트</b> 여성<b>니트</b> 여자<b>니트</b> 여성용 싱글 <b>니트</b> <b>아이스</b>",
      "link": "https://search.shopping.naver.com/catalog/42285261859",
      "image": "https://shopping-phinf.pstatic.net/main_4228526/42285261859.20230828202427.jpg",
      "lprice": "18030",
      "hprice": "",
      "mall_name": "네이버",
      "product_id": "42285261859",
      "category1": "패션의류",
      "category2": "여성의류",
      "category3": "니트",
      "category4": "풀오버"
    },
    {
      "title": "울<b>니트</b> 2023 여성용 <b>니트</b> <b>아이스</b> 실크 스웨터 라운드 넥 반팔 할로우 아웃 스타일 루즈핏 멋진 풀오버 새로운 패턴",
      "link": "https://smartstore.naver.com/main/products/10195599555",
      "image": "https://shopping-phinf.pstatic.net/main_8774010/87740103016.jpg",
      "lprice": "29440",
      "hprice": "",
      "mall_name": "해외구매4",
      "product_id": "87740103016",
      "category1": "패션의류",
      "category2": "여성의류",
      "category3": "니트",
      "category4": "풀오버"
    },
    {
      "title": "여성<b>니트</b>티 반팔 긴팔 베이직 풀오버 스웨터 <b>아이스</b> 코튼 <b>니트</b> 탑스 가을 캐주얼 티셔츠 라운드 넥 슬림 <b>겨울</b> 바닥 탑스",
      "link": "https://smartstore.naver.com/main/products/7335555056",
      "image": "https://shopping-phinf.pstatic.net/main_8488005/84880055378.jpg",
      "lprice": "31200",
      "hprice": "",
      "mall_name": "무심스토어 둘",
      "product_id": "84880055378",
      "category1": "패션의류",
      "category2": "여성의류",
      "category3": "니트",
      "category4": "풀오버"
    },
    {
      "title": "1+1 쿨<b>아이스</b> 반팔 <b>니트</b>티 루즈핏 리본 라운드넥 풀오버 상의 예쁜 중년여성 여름 <b>니트</b>  <b>핑크</b>+살구  L",
      "link": "https://link.coupang.com/re/PCSNAVERPCSDP?pageKey=9322887239&ctag=9322887239&lptag=P9322887239&itemId=27633334728&vendorItemId=94596133750&spec=10305199",
      "image": "https://shopping-phinf.pstatic.net/main_5860368/58603682122.jpg",
      "lprice": "27700",
      "hprice": "",
      "mall_name": "쿠팡",
      "product_id": "58603682122",
      "category1": "패션의류",
      "category2": "여성의류",
      "category3": "니트",
      "category4": "풀오버"
    },
    {
      "title": "여성 <b>니트</b> 반팔티 <b>니트</b>티 라운드 레인보우 컬러플한 루즈핏 라운드넥 <b>아이스</b> 반팔 티셔츠 <b>핑크</b>",
      "link": "https://smartstore.naver.com/main/products/12096369589",
      "image": "https://shopping-phinf.pstatic.net/main_8964088/89640880294.jpg",
      "lprice": "25400",
      "hprice": "",
      "mall_name": "selLua 셀루아샵",
      "product_id": "89640880294",
      "category1": "패션의류",
      "category2": "여성의류",
      "category3": "니트",
      "category4": "풀오버"
    },
    {
      "title": "여성 얇은 <b>아이스</b> 실크 <b>니트</b> 티 여름 라운드넥 <b>핑크</b>",
      "link": "https://smartstore.naver.com/main/products/11845723784",
      "image": "https://shopping-phinf.pstatic.net/main_8939023/89390234378.jpg",
      "lprice": "21900",
      "hprice": "",
      "mall_name": "제로투올샵",
      "product_id": "89390234378",
      "category1": "패션의류",
      "category2": "여성의류",
      "category3": "니트",
      "category4": "풀오버"
    },
    {
      "title": "기능성카라티 폴로<b>니트</b> 여자반팔 <b>아이스</b> 여름 슬림 가디건 <b>핑크</b>",
      "link": "https://smartstore.naver.com/main/products/8553507435",
      "image": "https://shopping-phinf.pstatic.net/main_8609800/86098007756.jpg",
      "lprice": "35030",
      "hprice": "",
      "mall_name": "쾌속직구",
      "product_id": "86098007756",
      "category1": "패션의류",
      "category2": "여성의류",
      "category3": "니트",
      "category4": "풀오버"
    },
    {
      "title": "여성 민소매 <b>니트</b> 브이넥 <b>아이스</b> 나시 여 봄여름 <b>핑크</b> 브이넥 민소매 레깅스 상의 정장 이",
      "link": "https://smartstore.naver.com/main/products/8770964481",
      "image": "https://shopping-phinf.pstatic.net/main_8631546/86315464799.jpg",
      "lprice": "49500",
      "hprice": "",
      "mall_name": "최강직구",
      "product_id": "86315464799",
      "category1": "패션의류",
      "category2": "여성의류",
      "category3": "니트",
      "category4": "풀오버"
    },
    {
      "title": "기능성카라티 폴로<b>니트</b> 여자반팔 여름 향기로운 <b>핑크</b> 얇은 <b>아이스</b> 숏",
      "link": "https://smartstore.naver.com/main/products/8553507411",
      "image": "https://shopping-phinf.pstatic.net/main_8609800/86098007734.jpg",
      "lprice": "29360",
      "hprice": "",
      "mall_name": "쾌속직구",
      "product_id": "86098007734",
      "category1": "패션의류",
      "category2": "여성의류",
      "category3": "니트",
      "category4": "풀오버"
    },
    {
      "title": "ICEbear 가을/ <b>겨울</b> 여성 스웨터 2 조각 정장 유행 풀오버 드레스 NB-2314",
      "link": "https://smartstore.naver.com/main/products/9420322787",
      "image": "https://shopping-phinf.pstatic.net/main_8696482/86964823110.jpg",
      "lprice": "66910",
      "hprice": "",
      "mall_name": "벨몬트마켓",
      "product_id": "86964823110",
      "category1": "패션의류",
      "category2": "여성의류",
      "category3": "니트",
      "category4": "풀오버"
    },
    {
      "title": "서양풍 여름 고급 여성 <b>아이스</b> 스팽글 반팔 <b>니트</b> 여 라운드 기질 상의  평균 크기  <b>핑크</b>",
      "link": "https://link.coupang.com/re/PCSNAVERPCSDP?pageKey=6900799323&ctag=6900799323&lptag=P6900799323&itemId=16596171477&vendorItemId=83781225300&spec=10305199",
      "image": "https://shopping-phinf.pstatic.net/main_5205985/52059855932.2.jpg",
      "lprice": "23000",
      "hprice": "",
      "mall_name": "쿠팡",
      "product_id": "52059855932",
      "category1": "패션의류",
      "category2": "여성의류",
      "category3": "니트",
      "category4": "풀오버"
    },
    {
      "title": "여름 카라 반팔 <b>니트</b> 크롭 스트라이프 시원한 <b>아이스</b> 소재 여성 상의(1+1상품으로 주문수량의 2배수량 배송)",
      "link": "https://smartstore.naver.com/main/products/13086330799",
      "image": "https://shopping-phinf.pstatic.net/main_9063084/90630841891.jpg",
      "lprice": "35480",
      "hprice": "",
      "mall_name": "핑크JOY",
      "product_id": "90630841891",
      "category1": "패션의류",
      "category2": "여성의류",
      "category3": "니트",
      "category4": "풀오버"
    },
    {
      "title": "<b>아이스</b>터치 카라 <b>니트</b>_<b>핑크</b> (클래식핏)",
      "link": "http://www.stco.co.kr/Detail/Index/DKTVB03CSP",
      "image": "https://shopping-phinf.pstatic.net/main_5909335/59093359405.jpg",
      "lprice": "29900",
      "hprice": "",
      "mall_name": "STCO",
      "product_id": "59093359405",
      "category1": "패션의류",
      "category2": "여성의류",
      "category3": "니트",
      "category4": "풀오버"
    },
    {
      "title": "삼제태전 여성 여름용 <b>아이스</b> 실크 <b>니트</b> 반팔 티셔츠 패셔너블한 얇은 루즈핏 빅사이즈  <b>핑크</b>  S",
      "link": "https://link.coupang.com/re/PCSNAVERPCSDP?pageKey=8870926951&ctag=8870926951&lptag=P8870926951&itemId=25880894441&vendorItemId=92866910468&spec=10305199",
      "image": "https://shopping-phinf.pstatic.net/main_5550089/55500893771.4.jpg",
      "lprice": "28900",
      "hprice": "",
      "mall_name": "쿠팡",
      "product_id": "55500893771",
      "category1": "패션의류",
      "category2": "여성의류",
      "category3": "니트",
      "category4": "풀오버"
    },
    {
      "title": "여름 얇은 <b>핑크</b> 긴팔 미디 <b>니트</b> 티셔츠 여성 <b>아이스</b> 실크 풀오버 티셔츠",
      "link": "https://smartstore.naver.com/main/products/11722183029",
      "image": "https://shopping-phinf.pstatic.net/main_8926669/89266693528.jpg",
      "lprice": "22960",
      "hprice": "",
      "mall_name": "바잉어스스토어",
      "product_id": "89266693528",
      "category1": "패션의류",
      "category2": "여성의류",
      "category3": "니트",
      "category4": "풀오버"
    },
    {
      "title": "여자 여름 <b>니트</b> 티 플리츠 얇은 <b>아이스</b> 쿨 반팔 그린 <b>핑크</b> 루즈핏",
      "link": "https://smartstore.naver.com/main/products/10788617756",
      "image": "https://shopping-phinf.pstatic.net/main_8833312/88333123744.jpg",
      "lprice": "19900",
      "hprice": "",
      "mall_name": "웨이홀세일",
      "product_id": "88333123744",
      "category1": "패션의류",
      "category2": "여성의류",
      "category3": "니트",
      "category4": "풀오버"
    },
    {
      "title": "여자 반팔 <b>니트</b> 여름 가을 티셔츠 여성 패션 넥 <b>핑크</b> 탑 얇은 <b>아이스</b> 실크 스웨터",
      "link": "https://smartstore.naver.com/main/products/6803760096",
      "image": "https://shopping-phinf.pstatic.net/main_8434826/84348260418.jpg",
      "lprice": "55660",
      "hprice": "",
      "mall_name": "리유진",
      "product_id": "84348260418",
      "category1": "패션의류",
      "category2": "여성의류",
      "category3": "니트",
      "category4": "풀오버"
    },
    {
      "title": "여성 <b>니트</b> 반팔티 라운드 비웬 U넥 스파클링 <b>핑크</b> 슬림 숏 <b>아이스</b> 슬림 맨투맨 티셔츠 반",
      "link": "https://smartstore.naver.com/main/products/8788090739",
      "image": "https://shopping-phinf.pstatic.net/main_8633259/86332591062.jpg",
      "lprice": "37000",
      "hprice": "",
      "mall_name": "직구항공",
      "product_id": "86332591062",
      "category1": "패션의류",
      "category2": "여성의류",
      "category3": "니트",
      "category4": "풀오버"
    },
    {
      "title": "<b>니트</b> 반팔티 티셔츠 V라인 <b>핑크</b> 프렌치 브이넥 <b>아이스</b> 정어깨 반팔티 여 도파민 코디 여름",
      "link": "https://smartstore.naver.com/main/products/8776005899",
      "image": "https://shopping-phinf.pstatic.net/main_8632050/86320506218.jpg",
      "lprice": "32250",
      "hprice": "",
      "mall_name": "제이원88",
      "product_id": "86320506218",
      "category1": "패션의류",
      "category2": "여성의류",
      "category3": "니트",
      "category4": "풀오버"
    },
    {
      "title": "여성 <b>니트</b> 박시 상의 <b>아이스</b> 반팔 티셔츠 여성 고급감 <b>핑크</b> 여름 여름옷 루즈핏 얇은",
      "link": "https://smartstore.naver.com/main/products/8939735861",
      "image": "https://shopping-phinf.pstatic.net/main_8648423/86484236183.jpg",
      "lprice": "49500",
      "hprice": "",
      "mall_name": "최강직구",
      "product_id": "86484236183",
      "category1": "패션의류",
      "category2": "여성의류",
      "category3": "니트",
      "category4": "풀오버"
    },
    {
      "title": "여성 크롭 <b>니트</b> 티셔츠 여름 <b>핑크</b> 반팔 여 펀칭 <b>아이스</b> 얇은 달콤한 하이웨스트 퍼프 소매",
      "link": "https://smartstore.naver.com/main/products/8772291285",
      "image": "https://shopping-phinf.pstatic.net/main_8631679/86316791605.jpg",
      "lprice": "34750",
      "hprice": "",
      "mall_name": "키즈캐슬1",
      "product_id": "86316791605",
      "category1": "패션의류",
      "category2": "여성의류",
      "category3": "니트",
      "category4": "풀오버"
    },
    {
      "title": "여성 <b>니트</b> 박시 상의 <b>아이스</b> 래쉬가드 여 여름 루즈핏 긴팔 티셔츠 <b>핑크</b> 얇은 풀오버",
      "link": "https://smartstore.naver.com/main/products/8939754494",
      "image": "https://shopping-phinf.pstatic.net/main_8648425/86484254812.jpg",
      "lprice": "32250",
      "hprice": "",
      "mall_name": "최강직구",
      "product_id": "86484254812",
      "category1": "패션의류",
      "category2": "여성의류",
      "category3": "니트",
      "category4": "풀오버"
    },
    {
      "title": "여자<b>니트</b> 여름 <b>아이스</b> 상의 얇은 쿨링 반팔 패션 펀칭 린넨 <b>니트</b> 티 sk1  XL  라이트<b>핑크</b>",
      "link": "https://link.coupang.com/re/PCSNAVERPCSDP?pageKey=8835422225&ctag=8835422225&lptag=P8835422225&itemId=25746894751&vendorItemId=92735227384&spec=10305199",
      "image": "https://shopping-phinf.pstatic.net/main_5528177/55281775891.13.jpg",
      "lprice": "38900",
      "hprice": "",
      "mall_name": "쿠팡",
      "product_id": "55281775891",
      "category1": "패션의류",
      "category2": "여성의류",
      "category3": "니트",
      "category4": "풀오버"
    },
    {
      "title": "<b>핑크</b> 래글런 소매 <b>아이스</b> 실크 <b>니트</b> 스웨터 반팔 티셔츠 여성용 여름 얇은 2024 새로운 컷 작은 남자 탑",
      "link": "https://smartstore.naver.com/main/products/10635007216",
      "image": "https://shopping-phinf.pstatic.net/main_8817951/88179513026.jpg",
      "lprice": "24700",
      "hprice": "",
      "mall_name": "만물상 꾸메",
      "product_id": "88179513026",
      "category1": "패션의류",
      "category2": "여성의류",
      "category3": "니트",
      "category4": "풀오버"
    },
    {
      "title": "<b>아이스</b> 여리 <b>니트</b>  베이비<b>핑크</b>  free",
      "link": "https://link.coupang.com/re/PCSNAVERPCSDP?pageKey=8051291119&ctag=8051291119&lptag=P8051291119&itemId=22582553594&vendorItemId=89624318192&spec=10305199",
      "image": "https://shopping-phinf.pstatic.net/main_4884812/48848129705.jpg",
      "lprice": "45000",
      "hprice": "",
      "mall_name": "쿠팡",
      "product_id": "48848129705",
      "category1": "패션의류",
      "category2": "여성의류",
      "category3": "니트",
      "category4": "풀오버"
    },
    {
      "title": "여름 중년 스웨터 실크 아름다운 레이스 <b>아이스</b> <b>니트</b> 여자 여성용 티셔츠  <b>핑크</b>색  L",
      "link": "https://link.coupang.com/re/PCSNAVERPCSDP?pageKey=8617057695&ctag=8617057695&lptag=P8617057695&itemId=24997675766&vendorItemId=92002880534&spec=10305199",
      "image": "https://shopping-phinf.pstatic.net/main_5712620/57126205625.jpg",
      "lprice": "55900",
      "hprice": "",
      "mall_name": "쿠팡",
      "product_id": "57126205625",
      "category1": "패션의류",
      "category2": "여성의류",
      "category3": "니트",
      "category4": "풀오버"
    },
    {
      "title": "(무료배송)플러스 사이즈 화이트 <b>니트</b> 여성 정장 <b>아이스</b> 실크 겉옷 민소매 상의 여름",
      "link": "https://smartstore.naver.com/main/products/10137468623",
      "image": "https://shopping-phinf.pstatic.net/main_8768197/87681971805.2.jpg",
      "lprice": "21100",
      "hprice": "",
      "mall_name": "인터내셔널컴퍼니",
      "product_id": "87681971805",
      "category1": "패션의류",
      "category2": "여성의류",
      "category3": "니트",
      "category4": "풀오버"
    },
    {
      "title": "Icebear 가을 <b>겨울</b> 여성 tracksuit 단색 후드 스웨터 정장 <b>니트</b> 투피스 세트 NB-2313",
      "link": "https://smartstore.naver.com/main/products/9420309254",
      "image": "https://shopping-phinf.pstatic.net/main_8696480/86964809577.jpg",
      "lprice": "69300",
      "hprice": "",
      "mall_name": "벨몬트마켓",
      "product_id": "86964809577",
      "category1": "패션의류",
      "category2": "여성의류",
      "category3": "니트",
      "category4": "풀오버"
    },
    {
      "title": "<b>아이스</b>블루 스노우 바라클라바 후드<b>니트</b> 귀여운 스웨터",
      "link": "https://smartstore.naver.com/main/products/9719930645",
      "image": "https://shopping-phinf.pstatic.net/main_8726443/87264432915.jpg",
      "lprice": "68900",
      "hprice": "",
      "mall_name": "민집보부상",
      "product_id": "87264432915",
      "category1": "패션의류",
      "category2": "여성의류",
      "category3": "니트",
      "category4": "풀오버"
    },
    {
      "title": "이른봄슬림핏펀칭플라워찡비즈반팔브이넥슬림<b>아이스</b><b>니트</b>상의여  XL  <b>핑크</b>",
      "link": "https://link.coupang.com/re/PCSNAVERPCSDP?pageKey=7426003198&ctag=7426003198&lptag=P7426003198&itemId=19275923748&vendorItemId=86390997713&spec=10305199",
      "image": "https://shopping-phinf.pstatic.net/main_5929938/59299385411.jpg",
      "lprice": "26500",
      "hprice": "",
      "mall_name": "쿠팡",
      "product_id": "59299385411",
      "category1": "패션의류",
      "category2": "여성의류",
      "category3": "니트",
      "category4": "풀오버"
    },
    {
      "title": "<b>아이스</b>터치 카라 반팔 <b>니트</b>_<b>핑크</b> (클래식핏)",
      "link": "http://www.stco.co.kr/Detail/Index/DKTXB02CSP",
      "image": "https://shopping-phinf.pstatic.net/main_5931748/59317485562.jpg",
      "lprice": "59900",
      "hprice": "",
      "mall_name": "STCO",
      "product_id": "59317485562",
      "category1": "패션의류",
      "category2": "여성의류",
      "category3": "니트",
      "category4": "풀오버"
    },
    {
      "title": "여름 여성 카라티 <b>아이스</b> 반팔<b>니트</b> 티셔츠 토끼 자수 배색<b>니트</b> 스트라이프티셔츠 단가라 반팔티 데일리 데이트룩 QOYO  L  <b>핑크</b>",
      "link": "https://link.coupang.com/re/PCSNAVERPCSDP?pageKey=8743405217&ctag=8743405217&lptag=P8743405217&itemId=25410579720&vendorItemId=92403977017&spec=10305199",
      "image": "https://shopping-phinf.pstatic.net/main_5540538/55405382468.jpg",
      "lprice": "25700",
      "hprice": "",
      "mall_name": "쿠팡",
      "product_id": "55405382468",
      "category1": "패션의류",
      "category2": "여성의류",
      "category3": "니트",
      "category4": "풀오버"
    },
    {
      "title": "ROYALBELLE 여성 라운드넥 빅사이즈 <b>아이스</b>실크 <b>니트</b>티 얇은소재 루즈핏 7부소매 <b>니트</b> F0080803  <b>핑크</b>  3XL",
      "link": "https://link.coupang.com/re/PCSNAVERPCSDP?pageKey=8976257849&ctag=8976257849&lptag=P8976257849&itemId=26276531496&vendorItemId=93254612442&spec=10305199",
      "image": "https://shopping-phinf.pstatic.net/main_5620821/56208210837.26.jpg",
      "lprice": "22200",
      "hprice": "",
      "mall_name": "쿠팡",
      "product_id": "56208210837",
      "category1": "패션의류",
      "category2": "여성의류",
      "category3": "니트",
      "category4": "풀오버"
    },
    {
      "title": "2025 여름 반팔 <b>아이스</b> 실크 <b>니트</b> V넥 루즈핏 슬림핏 얇은 상의 기품 있는 부드러운 티셔츠 여성용  <b>핑크</b>  모든 야드",
      "link": "https://link.coupang.com/re/PCSNAVERPCSDP?pageKey=8847044316&ctag=8847044316&lptag=P8847044316&itemId=25787604679&vendorItemId=92701382991&spec=10305199",
      "image": "https://shopping-phinf.pstatic.net/main_5534448/55344480966.46.jpg",
      "lprice": "14250",
      "hprice": "",
      "mall_name": "쿠팡",
      "product_id": "55344480966",
      "category1": "패션의류",
      "category2": "여성의류",
      "category3": "니트",
      "category4": "풀오버"
    },
    {
      "title": "Vezri 중년 여성용 봄 여름 <b>아이스</b> 쿨링 <b>니트</b> 루즈핏 시크한 빅사이즈 얇은 후드 반팔 티셔츠 WHY  <b>핑크</b>  2XL",
      "link": "https://link.coupang.com/re/PCSNAVERPCSDP?pageKey=8670035950&ctag=8670035950&lptag=V92966126346&itemId=25167957550&vendorItemId=92966126346&spec=10305199",
      "image": "https://shopping-phinf.pstatic.net/main_5577647/55776474205.jpg",
      "lprice": "16920",
      "hprice": "",
      "mall_name": "쿠팡",
      "product_id": "55776474205",
      "category1": "패션의류",
      "category2": "여성의류",
      "category3": "니트",
      "category4": "풀오버"
    },
    {
      "title": "<b>아이스</b>실크 가디건 브이넥 냉감 <b>니트</b> 초록색<b>니트</b> 여성,<b>핑크</b>색,XL",
      "link": "https://smartstore.naver.com/main/products/10745269434",
      "image": "https://shopping-phinf.pstatic.net/main_8828977/88289775356.1.jpg",
      "lprice": "79590",
      "hprice": "",
      "mall_name": "에스에이치글로벌5412",
      "product_id": "88289775356",
      "category1": "패션의류",
      "category2": "여성의류",
      "category3": "니트",
      "category4": "풀오버"
    },
    {
      "title": "<b>니트</b> 알파벳 오피스룩 <b>아이스</b> 유럽 여성반팔<b>니트</b> 맨투맨 티 <b>니트</b>티 여름 <b>핑크</b>",
      "link": "https://smartstore.naver.com/main/products/10964805605",
      "image": "https://shopping-phinf.pstatic.net/main_8850931/88509311648.jpg",
      "lprice": "52290",
      "hprice": "",
      "mall_name": "쎄이버",
      "product_id": "88509311648",
      "category1": "패션의류",
      "category2": "여성의류",
      "category3": "니트",
      "category4": "풀오버"
    },
    {
      "title": "여름<b>니트</b> 캐주얼 여자폴로카라티 <b>핑크</b> 티셔츠여름 <b>아이스</b> 반팔",
      "link": "https://smartstore.naver.com/main/products/8553542173",
      "image": "https://shopping-phinf.pstatic.net/main_8609804/86098042496.jpg",
      "lprice": "32330",
      "hprice": "",
      "mall_name": "쾌속직구",
      "product_id": "86098042496",
      "category1": "패션의류",
      "category2": "여성의류",
      "category3": "니트",
      "category4": "풀오버"
    },
    {
      "title": "여성을위한 <b>핑크</b> 티셔츠 여름 라운드 넥 스트라이프 <b>니트</b> 반팔 <b>아이스</b> 실크 얇은 루즈 스타일 탑 꾸안꾸",
      "link": "https://smartstore.naver.com/main/products/10690753916",
      "image": "https://shopping-phinf.pstatic.net/main_8823525/88235259838.jpg",
      "lprice": "37700",
      "hprice": "",
      "mall_name": "아이쉬몰",
      "product_id": "88235259838",
      "category1": "패션의류",
      "category2": "여성의류",
      "category3": "니트",
      "category4": "풀오버"
    },
    {
      "title": "여성 <b>니트</b> 반팔티 라운드 <b>아이스</b> 슬림핏 숏 상의 패션 <b>핑크</b> 티셔츠",
      "link": "https://smartstore.naver.com/main/products/8788070280",
      "image": "https://shopping-phinf.pstatic.net/main_8633257/86332570603.jpg",
      "lprice": "21500",
      "hprice": "",
      "mall_name": "최강직구",
      "product_id": "86332570603",
      "category1": "패션의류",
      "category2": "여성의류",
      "category3": "니트",
      "category4": "풀오버"
    },
    {
      "title": "<b>니트</b> 반팔티 티셔츠 V라인 <b>핑크</b> 숏 브이넥 반팔 <b>아이스</b> 가디건 여 여름 얇은 스트링 오버",
      "link": "https://smartstore.naver.com/main/products/8776062874",
      "image": "https://shopping-phinf.pstatic.net/main_8632056/86320563195.jpg",
      "lprice": "27480",
      "hprice": "",
      "mall_name": "직구항공",
      "product_id": "86320563195",
      "category1": "패션의류",
      "category2": "여성의류",
      "category3": "니트",
      "category4": "풀오버"
    },
    {
      "title": "여성 <b>아이스</b> 실크 얇은 플라잉 소매 <b>핑크 니트</b> 스웨터 컷아웃 슬림 크롭탑 디자인 감각 2024 여름 신상",
      "link": "https://smartstore.naver.com/main/products/12239088230",
      "image": "https://shopping-phinf.pstatic.net/main_8978359/89783598946.jpg",
      "lprice": "39300",
      "hprice": "",
      "mall_name": "오션시티2601",
      "product_id": "89783598946",
      "category1": "패션의류",
      "category2": "여성의류",
      "category3": "니트",
      "category4": "풀오버"
    },
    {
      "title": "드라마 옷 패션 돌싱글즈 우아한제국 힙하게 하트시그널 진주 비즈 반팔 스웨터, 얇은 <b>아이스</b> 실크 <b>니트</b> 풀오버, <b>핑크</b> 여름 탑 , 패션",
      "link": "https://smartstore.naver.com/main/products/9257627562",
      "image": "https://shopping-phinf.pstatic.net/main_8680212/86802127885.jpg",
      "lprice": "69700",
      "hprice": "",
      "mall_name": "플뤼데테",
      "product_id": "86802127885",
      "category1": "패션의류",
      "category2": "여성의류",
      "category3": "니트",
      "category4": "풀오버"
    },
    {
      "title": "vsyoy 새로운 미키 헤드 <b>아이스</b> 실크 <b>니트</b> 탑 <b>핑크</b> 소녀 퍼프 소매 짧은 소매 탑  <b>핑크</b> 미키 탑  모든 야드",
      "link": "https://link.coupang.com/re/PCSNAVERPCSDP?pageKey=7547709629&ctag=7547709629&lptag=P7547709629&itemId=19856020277&vendorItemId=86957098332&spec=10305199",
      "image": "https://shopping-phinf.pstatic.net/main_5808251/58082512696.jpg",
      "lprice": "42710",
      "hprice": "",
      "mall_name": "쿠팡",
      "product_id": "58082512696",
      "category1": "패션의류",
      "category2": "여성의류",
      "category3": "니트",
      "category4": "풀오버"
    },
    {
      "title": "여름 가디건 꾸안꾸 여자 <b>핑크</b> <b>아이스</b> <b>니트</b> 시스루 에어컨",
      "link": "https://smartstore.naver.com/main/products/6671979948",
      "image": "https://shopping-phinf.pstatic.net/main_8421648/84216480270.jpg",
      "lprice": "17450",
      "hprice": "",
      "mall_name": "무한직구",
      "product_id": "84216480270",
      "category1": "패션의류",
      "category2": "여성의류",
      "category3": "니트",
      "category4": "카디건"
    },
    {
      "title": "브이넥 프릴 <b>핑크</b> <b>아이스</b><b>니트</b> 가디건 일일드라마 연예인스타일",
      "link": "https://smartstore.naver.com/main/products/11589674883",
      "image": "https://shopping-phinf.pstatic.net/main_8913418/89134185289.jpg",
      "lprice": "34100",
      "hprice": "",
      "mall_name": "RAMIYA",
      "product_id": "89134185289",
      "category1": "패션의류",
      "category2": "여성의류",
      "category3": "니트",
      "category4": "카디건"
    },
    {
      "title": "여름<b>니트</b> 여름 의류 뉴 <b>핑크</b> 이너웨어 탑 <b>아이스</b> 실크 <b>니트</b> 반팔 숄더 퍼프 슬리브 티셔츠 여성용",
      "link": "https://smartstore.naver.com/main/products/8519341585",
      "image": "https://shopping-phinf.pstatic.net/main_8606384/86063841908.jpg",
      "lprice": "25930",
      "hprice": "",
      "mall_name": "엠엔제이06",
      "product_id": "86063841908",
      "category1": "패션의류",
      "category2": "여성의류",
      "category3": "니트",
      "category4": "풀오버"
    },
    {
      "title": "스타일아유 예쁜 반팔 여성 데일리룩 진주단추 티셔츠 <b>아이스</b> 프렌치 KN2095 얇은 <b>니트</b> <b>핑크</b>",
      "link": "https://smartstore.naver.com/main/products/12393987196",
      "image": "https://shopping-phinf.pstatic.net/main_8993849/89938497921.jpg",
      "lprice": "43000",
      "hprice": "",
      "mall_name": "릴루베마켓",
      "product_id": "89938497921",
      "category1": "패션의류",
      "category2": "여성의류",
      "category3": "니트",
      "category4": "풀오버"
    },
    {
      "title": "<b>니트</b> 반팔티 <b>니트</b>티 라운드 라운드넥 <b>핑크</b> 티셔츠 <b>아이스</b> 루즈핏 반팔 컬러플한 에메랄드그린 500장부터",
      "link": "https://smartstore.naver.com/main/products/12315658890",
      "image": "https://shopping-phinf.pstatic.net/main_8986016/89860169607.jpg",
      "lprice": "23730",
      "hprice": "",
      "mall_name": "픽앤딜리버리",
      "product_id": "89860169607",
      "category1": "패션의류",
      "category2": "여성의류",
      "category3": "니트",
      "category4": "풀오버"
    },
    {
      "title": "케시미어<b>니트</b> 한국 시크 가을 <b>겨울</b> 칼라 실크 <b>니트</b>웨어 여성 탑 슬리브 버블 <b>아이스</b> 쿨 빈티지 <b>니트</b> 스웨터 스퀘어 긴팔",
      "link": "https://smartstore.naver.com/main/products/12896330742",
      "image": "https://shopping-phinf.pstatic.net/main_9044084/90440841734.jpg",
      "lprice": "32490",
      "hprice": "",
      "mall_name": "거니종합몰10",
      "product_id": "90440841734",
      "category1": "패션의류",
      "category2": "여성의류",
      "category3": "니트",
      "category4": "풀오버"
    },
    {
      "title": "여름 루즈핏 시스루 <b>니트</b> 긴팔 여성 <b>아이스</b>탑",
      "link": "https://smartstore.naver.com/main/products/11830699060",
      "image": "https://shopping-phinf.pstatic.net/main_8937520/89375209648.jpg",
      "lprice": "38800",
      "hprice": "",
      "mall_name": "미도리샵",
      "product_id": "89375209648",
      "category1": "패션의류",
      "category2": "여성의류",
      "category3": "니트",
      "category4": "풀오버"
    }
  ]
}